{
"type": "FeatureCollection",
"name": "pibor_wells_new_failed",
"crs": { "type": "name", "properties": { "name": "urn:ogc:def:crs:OGC:1.3:CRS84" } },
"features": [
{ "type": "Feature", "properties": { "Name": "Failed", "description": "Payam: Vertet<br>Boma: Vertet<br>Lat: 6.680517<br>Long: 33.2065<br>Work Performed: Drilled <br>Date: 3\/20\/2015<br>Yield m3\/hour: N\/F<br>Total Depth: 108<br>Main Water Strike: 26<br>Static Water Level: 50<br>Dynamic Water Level: 85<br>Elevation: 410<br>Contractor: Balaji<br>Comments: Not functioning- Not flushed properly, polymer clogging screen casing  ", "timestamp": null, "begin": null, "end": null, "altitudeMode": null, "tessellate": -1, "extrude": 0, "visibility": -1, "drawOrder": null, "icon": null, "Payam": "Vertet", "Boma": "Vertet", "Lat": "6.680517", "Long": "33.2065", "Work_Performed": "Drilled ", "Date": "3\/20\/2015", "Yield_m3_hour": "N\/F", "Total_Depth": "108.0", "Main_Water_Strike": "26.0", "Static_Water_Level": "50.0", "Dynamic_Water_Level": "85.0", "Elevation": "410.0", "Contractor": "Balaji", "Comments": "Not functioning- Not flushed properly, polymer clogging screen casing  ", "gx_media_links": null }, "geometry": { "type": "Point", "coordinates": [ 33.2065, 6.680517, 0.0 ] } },
{ "type": "Feature", "properties": { "Name": "Failed", "description": "Payam: Vertet<br>Boma: Thawalwal<br>Lat: 6.662883<br>Long: 33.247817<br>Work Performed: Drilled<br>Date: 3\/27\/2015<br>Yield m3\/hour: N\/F<br>Total Depth: 103<br>Main Water Strike: 60<br>Static Water Level: 58<br>Dynamic Water Level: 95<br>Elevation: 400<br>Contractor: Balaji<br>Comments: Not functioning- Not flushed properly, polymer clogging screen casing  ", "timestamp": null, "begin": null, "end": null, "altitudeMode": null, "tessellate": -1, "extrude": 0, "visibility": -1, "drawOrder": null, "icon": null, "Payam": "Vertet", "Boma": "Thawalwal", "Lat": "6.662883", "Long": "33.247817", "Work_Performed": "Drilled", "Date": "3\/27\/2015", "Yield_m3_hour": "N\/F", "Total_Depth": "103.0", "Main_Water_Strike": "60.0", "Static_Water_Level": "58.0", "Dynamic_Water_Level": "95.0", "Elevation": "400.0", "Contractor": "Balaji", "Comments": "Not functioning- Not flushed properly, polymer clogging screen casing  ", "gx_media_links": null }, "geometry": { "type": "Point", "coordinates": [ 33.247817, 6.662883, 0.0 ] } },
{ "type": "Feature", "properties": { "Name": "Failed", "description": "Payam: Bubuzen<br>Boma: Bubuzen<br>Lat: 6.930383<br>Long: 33.04065<br>Work Performed: Drilled<br>Date: 3\/29\/2015<br>Yield m3\/hour: N\/F<br>Total Depth: <br>Main Water Strike: <br>Static Water Level: <br>Dynamic Water Level: <br>Elevation: <br>Contractor: Balaji<br>Comments: Not functioning- Not flushed properly, polymer clogging screen casing  ", "timestamp": null, "begin": null, "end": null, "altitudeMode": null, "tessellate": -1, "extrude": 0, "visibility": -1, "drawOrder": null, "icon": null, "Payam": "Bubuzen", "Boma": "Bubuzen", "Lat": "6.930383", "Long": "33.04065", "Work_Performed": "Drilled", "Date": "3\/29\/2015", "Yield_m3_hour": "N\/F", "Total_Depth": "", "Main_Water_Strike": "", "Static_Water_Level": "", "Dynamic_Water_Level": "", "Elevation": "", "Contractor": "Balaji", "Comments": "Not functioning- Not flushed properly, polymer clogging screen casing  ", "gx_media_links": null }, "geometry": { "type": "Point", "coordinates": [ 33.04065, 6.930383, 0.0 ] } }
]
}
