{
"type": "FeatureCollection",
"name": "SSD_food_access",
"crs": { "type": "name", "properties": { "name": "urn:ogc:def:crs:OGC:1.3:CRS84" } },
"features": [
{ "type": "Feature", "properties": { "Name": "Seed and Agricultural Tools Distribution \n", "description": "We distributed cereal crop seeds and agricultural tools. We conducted training sessions on good agronomic practices.", "timestamp": null, "begin": null, "end": null, "altitudeMode": null, "tessellate": -1, "extrude": 0, "visibility": -1, "drawOrder": null, "icon": null }, "geometry": { "type": "Point", "coordinates": [ 27.827201, 7.6748167, 0.0 ] } },
{ "type": "Feature", "properties": { "Name": "Fishing Kits and Vegetable Garden Tools and Seeds Distribution\n", "description": "We provided vegetable growing and fishing kits. We conducted training on more efficient fishing practices.", "timestamp": null, "begin": null, "end": null, "altitudeMode": null, "tessellate": -1, "extrude": 0, "visibility": -1, "drawOrder": null, "icon": null }, "geometry": { "type": "Point", "coordinates": [ 28.2391883, 7.5495873, 0.0 ] } }
]
}
